{
  "overgrow": [
    "bulbasaur",
    "ivysaur",
    "venusaur",
    "chikorita",
    "bayleef",
    "meganium",
    "treecko",
    "grovyle",
    "sceptile",
    "turtwig",
    "grotle",
    "torterra",
    "snivy",
    "servine",
    "serperior",
    "pansage",
    "simisage",
    "chespin",
    "quilladin",
    "chesnaught",
    "rowlet",
    "dartrix",
    "decidueye",
    "decidueye-hisui",
    "grookey",
    "thwackey",
    "rillaboom",
    "sprigatito",
    "floragato",
    "meowscarada"
  ],
  "chlorophyll": [
    "bulbasaur",
    "ivysaur",
    "venusaur",
    "oddish",
    "gloom",
    "vileplume",
    "bellsprout",
    "weepinbell",
    "victreebel",
    "exeggcute",
    "exeggutor",
    "tangela",
    "bellossom",
    "hoppip",
    "skiploom",
    "jumpluff",
    "sunkern",
    "sunflora",
    "seedot",
    "nuzleaf",
    "shiftry",
    "tropius",
    "cherubi",
    "tangrowth",
    "leafeon",
    "sewaddle",
    "swadloon",
    "leavanny",
    "cottonee",
    "whimsicott",
    "petilil",
    "lilligant",
    "lilligant-hisui",
    "maractus",
    "deerling",
    "sawsbuck",
    "capsakid",
    "scovillain"
  ],
  "thick-fat": [
    "venusaur-mega",
    "rattata-alola",
    "raticate-alola",
    "seel",
    "dewgong",
    "snorlax",
    "marill",
    "azumarill",
    "swinub",
    "piloswine",
    "miltank",
    "makuhita",
    "hariyama",
    "azurill",
    "spoink",
    "grumpig",
    "spheal",
    "sealeo",
    "walrein",
    "purugly",
    "munchlax",
    "mamoswine",
    "tepig",
    "pignite",
    "appletun",
    "lechonk",
    "oinkologne",
    "oinkologne-f",
    "cetoddle",
    "cetitan"
  ],
  "blaze": [
    "charmander",
    "charmeleon",
    "charizard",
    "cyndaquil",
    "quilava",
    "typhlosion",
    "typhlosion-hisui",
    "torchic",
    "combusken",
    "blaziken",
    "chimchar",
    "monferno",
    "infernape",
    "tepig",
    "pignite",
    "emboar",
    "pansear",
    "simisear",
    "fennekin",
    "braixen",
    "delphox",
    "litten",
    "torracat",
    "incineroar",
    "scorbunny",
    "raboot",
    "cinderace",
    "fuecoco",
    "crocalor",
    "skeledirge"
  ],
  "solar-power": [
    "charmander",
    "charmeleon",
    "charizard",
    "sunkern",
    "sunflora",
    "houndoom-mega",
    "tropius",
    "helioptile",
    "heliolisk"
  ],
  "tough-claws": [
    "charizard-mega-x",
    "meowth-galar",
    "aerodactyl-mega",
    "metagross-mega",
    "binacle",
    "barbaracle",
    "barbaracle-mega",
    "lycanroc-dusk",
    "perrserker"
  ],
  "drought": [
    "charizard-mega-y",
    "vulpix",
    "ninetales",
    "torkoal",
    "groudon"
  ],
  "torrent": [
    "squirtle",
    "wartortle",
    "blastoise",
    "totodile",
    "croconaw",
    "feraligatr",
    "mudkip",
    "marshtomp",
    "swampert",
    "piplup",
    "prinplup",
    "empoleon",
    "oshawott",
    "dewott",
    "samurott",
    "samurott-hisui",
    "panpour",
    "simipour",
    "froakie",
    "frogadier",
    "greninja",
    "popplio",
    "brionne",
    "primarina",
    "sobble",
    "drizzile",
    "inteleon",
    "quaxly",
    "quaxwell",
    "quaquaval"
  ],
  "rain-dish": [
    "squirtle",
    "wartortle",
    "blastoise",
    "tentacool",
    "tentacruel",
    "lotad",
    "lombre",
    "ludicolo",
    "wingull",
    "pelipper",
    "surskit",
    "morelull",
    "shiinotic"
  ],
  "mega-launcher": [
    "blastoise-mega",
    "clauncher",
    "clawitzer"
  ],
  "shield-dust": [
    "caterpie",
    "weedle",
    "venomoth",
    "wurmple",
    "dustox",
    "scatterbug",
    "vivillon",
    "vivillon-fancy",
    "vivillon-pokeball",
    "cutiefly",
    "ribombee",
    "snom",
    "frosmoth"
  ],
  "run-away": [
    "caterpie",
    "weedle",
    "rattata",
    "raticate",
    "oddish",
    "venonat",
    "ponyta",
    "ponyta-galar",
    "rapidash",
    "rapidash-galar",
    "doduo",
    "dodrio",
    "eevee",
    "eevee-starter",
    "sentret",
    "furret",
    "aipom",
    "dunsparce",
    "snubbull",
    "poochyena",
    "wurmple",
    "nincada",
    "kricketot",
    "pachirisu",
    "buneary",
    "patrat",
    "lillipup",
    "nickit",
    "thievul",
    "wooloo",
    "tandemaus",
    "maschiff",
    "dudunsparce",
    "dudunsparce-three-segment",
    "gimmighoul-roaming"
  ],
  "shed-skin": [
    "metapod",
    "kakuna",
    "ekans",
    "arbok",
    "dratini",
    "dragonair",
    "pupitar",
    "silcoon",
    "cascoon",
    "seviper",
    "kricketot",
    "burmy",
    "scraggy",
    "scrafty",
    "scrafty-mega",
    "karrablast",
    "spewpa",
    "silicobra",
    "sandaconda",
    "rellor",
    "cyclizar"
  ],
  "compound-eyes": [
    "butterfree",
    "venonat",
    "yanma",
    "dustox",
    "nincada",
    "joltik",
    "galvantula",
    "scatterbug",
    "vivillon",
    "vivillon-fancy",
    "vivillon-pokeball",
    "blipbug",
    "dottler",
    "rellor"
  ],
  "tinted-lens": [
    "butterfree",
    "venonat",
    "venomoth",
    "hoothoot",
    "noctowl",
    "illumise",
    "mothim",
    "yanmega",
    "sigilyph",
    "braviary-hisui",
    "nymble",
    "lokix"
  ],
  "swarm": [
    "beedrill",
    "scyther",
    "ledyba",
    "ledian",
    "spinarak",
    "ariados",
    "scizor",
    "heracross",
    "beautifly",
    "volbeat",
    "kricketune",
    "mothim",
    "sewaddle",
    "leavanny",
    "venipede",
    "whirlipede",
    "scolipede",
    "scolipede-mega",
    "karrablast",
    "escavalier",
    "joltik",
    "galvantula",
    "durant",
    "larvesta",
    "volcarona",
    "grubbin",
    "blipbug",
    "dottler",
    "orbeetle",
    "kleavor",
    "nymble",
    "lokix"
  ],
  "sniper": [
    "beedrill",
    "spearow",
    "fearow",
    "horsea",
    "seadra",
    "spinarak",
    "ariados",
    "remoraid",
    "octillery",
    "kingdra",
    "skorupi",
    "drapion",
    "binacle",
    "barbaracle",
    "barbaracle-mega",
    "sobble",
    "drizzile",
    "inteleon"
  ],
  "adaptability": [
    "beedrill-mega",
    "eevee",
    "eevee-starter",
    "corphish",
    "crawdaunt",
    "feebas",
    "lucario-mega",
    "lucario-mega-z",
    "porygon-z",
    "basculin",
    "basculin-blue-striped",
    "basculin-white-striped",
    "skrelp",
    "dragalge",
    "dragalge-mega",
    "yungoos",
    "gumshoos",
    "basculegion",
    "basculegion-f",
    "glimmora-mega"
  ],
  "keen-eye": [
    "pidgey",
    "pidgeotto",
    "pidgeot",
    "spearow",
    "fearow",
    "farfetch-d",
    "hitmonchan",
    "sentret",
    "furret",
    "hoothoot",
    "noctowl",
    "sneasel",
    "sneasel-hisui",
    "skarmory",
    "wingull",
    "pelipper",
    "sableye",
    "starly",
    "glameow",
    "stunky",
    "skuntank",
    "chatot",
    "skorupi",
    "drapion",
    "patrat",
    "watchog",
    "ducklett",
    "swanna",
    "rufflet",
    "braviary",
    "braviary-hisui",
    "espurr",
    "meowstic",
    "meowstic-f",
    "pikipek",
    "trumbeak",
    "toucannon",
    "rockruff",
    "lycanroc",
    "lycanroc-midnight",
    "rookidee",
    "corvisquire",
    "bombirdier"
  ],
  "tangled-feet": [
    "pidgey",
    "pidgeotto",
    "pidgeot",
    "doduo",
    "dodrio",
    "spinda",
    "chatot",
    "mr-rime",
    "flamigo"
  ],
  "big-pecks": [
    "pidgey",
    "pidgeotto",
    "pidgeot",
    "chatot",
    "pidove",
    "tranquill",
    "unfezant",
    "ducklett",
    "swanna",
    "vullaby",
    "mandibuzz",
    "fletchling",
    "rookidee",
    "corvisquire",
    "bombirdier"
  ],
  "no-guard": [
    "pidgeot-mega",
    "machop",
    "machoke",
    "machamp",
    "karrablast",
    "golett",
    "golurk",
    "honedge",
    "doublade",
    "hawlucha-mega",
    "lycanroc-midnight"
  ],
  "guts": [
    "rattata",
    "raticate",
    "machop",
    "machoke",
    "machamp",
    "flareon",
    "heracross",
    "ursaring",
    "tyrogue",
    "larvitar",
    "taillow",
    "swellow",
    "makuhita",
    "hariyama",
    "shinx",
    "luxio",
    "luxray",
    "timburr",
    "gurdurr",
    "conkeldurr",
    "throh",
    "obstagoon",
    "ursaluna",
    "squawkabilly",
    "squawkabilly-blue"
  ],
  "hustle": [
    "rattata",
    "rattata-alola",
    "raticate",
    "raticate-alola",
    "nidoran-f",
    "nidorina",
    "nidoran-m",
    "nidorino",
    "togepi",
    "togetic",
    "corsola",
    "remoraid",
    "delibird",
    "combee",
    "togekiss",
    "lilligant-hisui",
    "darumaka",
    "darumaka-galar",
    "rufflet",
    "durant",
    "deino",
    "zweilous",
    "flapple",
    "dracozolt",
    "squawkabilly",
    "squawkabilly-blue",
    "squawkabilly-yellow",
    "squawkabilly-white"
  ],
  "gluttony": [
    "rattata-alola",
    "raticate-alola",
    "bellsprout",
    "weepinbell",
    "victreebel",
    "slowpoke-galar",
    "grimer-alola",
    "muk-alola",
    "snorlax",
    "shuckle",
    "zigzagoon",
    "zigzagoon-galar",
    "linoone",
    "linoone-galar",
    "gulpin",
    "swalot",
    "spoink",
    "grumpig",
    "munchlax",
    "pansage",
    "simisage",
    "pansear",
    "simisear",
    "panpour",
    "simipour",
    "heatmor",
    "skwovet",
    "greedent",
    "applin",
    "flapple",
    "appletun",
    "lechonk",
    "oinkologne",
    "oinkologne-f",
    "dipplin"
  ],
  "intimidate": [
    "ekans",
    "arbok",
    "growlithe",
    "growlithe-hisui",
    "arcanine",
    "arcanine-hisui",
    "tauros",
    "tauros-paldea-combat",
    "tauros-paldea-blaze",
    "tauros-paldea-aqua",
    "gyarados",
    "snubbull",
    "granbull",
    "qwilfish",
    "qwilfish-hisui",
    "stantler",
    "hitmontop",
    "mightyena",
    "masquerain",
    "mawile",
    "manectric-mega",
    "salamence",
    "staravia",
    "staraptor",
    "staraptor-mega",
    "shinx",
    "luxio",
    "luxray",
    "herdier",
    "stoutland",
    "sandile",
    "krokorok",
    "krookodile",
    "scraggy",
    "scrafty",
    "scrafty-mega",
    "landorus-therian",
    "litten",
    "torracat",
    "incineroar",
    "wyrdeer",
    "overqwil",
    "squawkabilly",
    "squawkabilly-blue",
    "squawkabilly-yellow",
    "squawkabilly-white",
    "maschiff",
    "mabosstiff"
  ],
  "unnerve": [
    "ekans",
    "arbok",
    "meowth",
    "meowth-galar",
    "persian",
    "aerodactyl",
    "mewtwo",
    "ursaring",
    "houndour",
    "houndoom",
    "tyranitar",
    "masquerain",
    "vespiquen",
    "joltik",
    "galvantula",
    "axew",
    "fraxure",
    "haxorus",
    "litleo",
    "pyroar",
    "pyroar-mega",
    "bewear",
    "rookidee",
    "corvisquire",
    "corviknight",
    "calyrex",
    "ursaluna"
  ],
  "static": [
    "pikachu",
    "pikachu-original",
    "pikachu-hoenn",
    "pikachu-sinnoh",
    "pikachu-unova",
    "pikachu-kalos",
    "pikachu-alola",
    "pikachu-partner",
    "pikachu-starter",
    "pikachu-world",
    "raichu",
    "voltorb",
    "voltorb-hisui",
    "electrode",
    "electrode-hisui",
    "electabuzz",
    "zapdos",
    "pichu",
    "pichu-spiky-eared",
    "mareep",
    "flaaffy",
    "ampharos",
    "elekid",
    "electrike",
    "manectric",
    "emolga",
    "stunfisk",
    "toxel",
    "arctozolt",
    "pawmi",
    "tadbulb",
    "bellibolt"
  ],
  "lightning-rod": [
    "pikachu",
    "pikachu-cosplay",
    "pikachu-rock-star",
    "pikachu-belle",
    "pikachu-pop-star",
    "pikachu-phd",
    "pikachu-libre",
    "pikachu-original",
    "pikachu-hoenn",
    "pikachu-sinnoh",
    "pikachu-unova",
    "pikachu-kalos",
    "pikachu-alola",
    "pikachu-partner",
    "pikachu-starter",
    "pikachu-world",
    "raichu",
    "cubone",
    "marowak",
    "marowak-alola",
    "rhyhorn",
    "rhydon",
    "goldeen",
    "seaking",
    "pichu",
    "sceptile-mega",
    "electrike",
    "manectric",
    "plusle",
    "rhyperior",
    "blitzle",
    "zebstrika",
    "togedemaru",
    "pincurchin"
  ],
  "surge-surfer": [
    "raichu-alola",
    "raichu-mega-x",
    "raichu-mega-y"
  ],
  "sand-veil": [
    "sandshrew",
    "sandslash",
    "diglett",
    "diglett-alola",
    "dugtrio",
    "dugtrio-alola",
    "geodude",
    "graveler",
    "golem",
    "gligar",
    "phanpy",
    "donphan",
    "larvitar",
    "cacnea",
    "cacturne",
    "gible",
    "gabite",
    "garchomp",
    "gliscor",
    "stunfisk",
    "helioptile",
    "heliolisk",
    "sandygast",
    "palossand",
    "silicobra",
    "sandaconda",
    "wiglett",
    "wugtrio",
    "orthworm"
  ],
  "sand-rush": [
    "sandshrew",
    "sandslash",
    "herdier",
    "stoutland",
    "drilbur",
    "excadrill",
    "lycanroc",
    "dracozolt",
    "dracovish",
    "houndstone"
  ],
  "snow-cloak": [
    "sandshrew-alola",
    "sandslash-alola",
    "vulpix-alola",
    "ninetales-alola",
    "articuno",
    "swinub",
    "piloswine",
    "glaceon",
    "mamoswine",
    "froslass",
    "vanillite",
    "vanillish",
    "cubchoo",
    "beartic",
    "cetoddle"
  ],
  "slush-rush": [
    "sandshrew-alola",
    "sandslash-alola",
    "cubchoo",
    "beartic",
    "arctozolt",
    "arctovish",
    "cetitan"
  ],
  "poison-point": [
    "nidoran-f",
    "nidorina",
    "nidoqueen",
    "nidoran-m",
    "nidorino",
    "nidoking",
    "seadra",
    "wooper-paldea",
    "qwilfish",
    "qwilfish-hisui",
    "roselia",
    "budew",
    "roserade",
    "venipede",
    "whirlipede",
    "scolipede",
    "scolipede-mega",
    "skrelp",
    "dragalge",
    "dragalge-mega",
    "overqwil",
    "clodsire"
  ],
  "rivalry": [
    "nidoran-f",
    "nidorina",
    "nidoqueen",
    "nidoran-m",
    "nidorino",
    "nidoking",
    "beautifly",
    "shinx",
    "luxio",
    "luxray",
    "pidove",
    "tranquill",
    "unfezant",
    "axew",
    "fraxure",
    "haxorus",
    "litleo",
    "pyroar",
    "pyroar-mega"
  ],
  "sheer-force": [
    "nidoqueen",
    "nidoking",
    "krabby",
    "kingler",
    "tauros",
    "totodile",
    "croconaw",
    "feraligatr",
    "steelix",
    "makuhita",
    "hariyama",
    "mawile",
    "camerupt-mega",
    "trapinch",
    "bagon",
    "cranidos",
    "rampardos",
    "timburr",
    "gurdurr",
    "conkeldurr",
    "darmanitan",
    "druddigon",
    "rufflet",
    "braviary",
    "braviary-hisui",
    "landorus",
    "toucannon",
    "cufant",
    "copperajah",
    "kleavor",
    "squawkabilly-yellow",
    "squawkabilly-white",
    "cetoddle",
    "cetitan"
  ],
  "cute-charm": [
    "clefairy",
    "clefable",
    "jigglypuff",
    "wigglytuff",
    "cleffa",
    "igglybuff",
    "skitty",
    "delcatty",
    "milotic",
    "lopunny",
    "minccino",
    "cinccino",
    "sylveon",
    "stufful",
    "enamorus"
  ],
  "magic-guard": [
    "clefairy",
    "clefable",
    "abra",
    "kadabra",
    "alakazam",
    "cleffa",
    "sigilyph",
    "solosis",
    "duosion",
    "reuniclus"
  ],
  "friend-guard": [
    "clefairy",
    "jigglypuff",
    "cleffa",
    "igglybuff",
    "happiny",
    "scatterbug",
    "spewpa",
    "vivillon",
    "vivillon-fancy",
    "vivillon-pokeball",
    "maushold",
    "maushold-four"
  ],
  "unaware": [
    "clefable",
    "wooper",
    "wooper-paldea",
    "quagsire",
    "bidoof",
    "bibarel",
    "woobat",
    "swoobat",
    "pyukumuku",
    "cosmog",
    "fuecoco",
    "crocalor",
    "skeledirge",
    "dondozo",
    "clodsire"
  ],
  "magic-bounce": [
    "clefable-mega",
    "natu",
    "xatu",
    "espeon",
    "sableye-mega",
    "absol-mega",
    "absol-mega-z",
    "diancie-mega",
    "hatenna",
    "hattrem",
    "hatterene"
  ],
  "flash-fire": [
    "vulpix",
    "ninetales",
    "growlithe",
    "growlithe-hisui",
    "arcanine",
    "arcanine-hisui",
    "ponyta",
    "rapidash",
    "flareon",
    "cyndaquil",
    "quilava",
    "typhlosion",
    "houndour",
    "houndoom",
    "heatran",
    "heatran-mega",
    "litwick",
    "lampent",
    "chandelure",
    "heatmor",
    "rolycoly",
    "carkol",
    "coalossal",
    "sizzlipede",
    "centiskorch",
    "charcadet",
    "armarouge",
    "ceruledge"
  ],
  "snow-warning": [
    "vulpix-alola",
    "ninetales-alola",
    "snover",
    "abomasnow",
    "abomasnow-mega",
    "froslass-mega",
    "vanilluxe",
    "amaura",
    "aurorus"
  ],
  "competitive": [
    "jigglypuff",
    "wigglytuff",
    "articuno-galar",
    "igglybuff",
    "milotic",
    "piplup",
    "prinplup",
    "empoleon",
    "gothita",
    "gothorita",
    "gothitelle",
    "meowstic-f",
    "boltund",
    "wattrel",
    "kilowattrel"
  ],
  "frisk": [
    "wigglytuff",
    "exeggutor-alola",
    "typhlosion-hisui",
    "sentret",
    "furret",
    "yanma",
    "stantler",
    "shuppet",
    "banette",
    "duskull",
    "dusclops",
    "yanmega",
    "dusknoir",
    "gothita",
    "gothorita",
    "gothitelle",
    "phantump",
    "trevenant",
    "pumpkaboo",
    "pumpkaboo-small",
    "pumpkaboo-large",
    "pumpkaboo-super",
    "gourgeist",
    "gourgeist-small",
    "gourgeist-large",
    "gourgeist-super",
    "noibat",
    "noivern",
    "orbeetle",
    "impidimp",
    "morgrem",
    "grimmsnarl",
    "wyrdeer",
    "flittle",
    "espathra",
    "munkidori"
  ],
  "inner-focus": [
    "zubat",
    "golbat",
    "abra",
    "kadabra",
    "alakazam",
    "farfetch-d",
    "drowzee",
    "hypno",
    "hitmonchan",
    "kangaskhan",
    "dragonite",
    "crobat",
    "umbreon",
    "girafarig",
    "sneasel",
    "sneasel-hisui",
    "raikou",
    "entei",
    "suicune",
    "snorunt",
    "glalie",
    "riolu",
    "lucario",
    "gallade-mega",
    "throh",
    "sawk",
    "darumaka",
    "darumaka-galar",
    "mienfoo",
    "mienshao",
    "pawniard",
    "bisharp",
    "mudbray",
    "mudsdale",
    "oranguru",
    "indeedee",
    "kubfu",
    "annihilape"
  ],
  "infiltrator": [
    "zubat",
    "golbat",
    "crobat",
    "hoppip",
    "skiploom",
    "jumpluff",
    "ninjask",
    "seviper",
    "spiritomb",
    "cottonee",
    "whimsicott",
    "litwick",
    "lampent",
    "chandelure",
    "chandelure-mega",
    "espurr",
    "meowstic",
    "meowstic-f",
    "inkay",
    "malamar",
    "malamar-mega",
    "noibat",
    "noivern",
    "dreepy",
    "drakloak",
    "dragapult",
    "bramblin",
    "brambleghast"
  ],
  "stench": [
    "gloom",
    "grimer",
    "muk",
    "koffing",
    "weezing",
    "stunky",
    "skuntank",
    "trubbish",
    "garbodor"
  ],
  "effect-spore": [
    "vileplume",
    "paras",
    "parasect",
    "shroomish",
    "breloom",
    "foongus",
    "amoonguss",
    "morelull",
    "shiinotic",
    "gossifleur",
    "eldegoss"
  ],
  "dry-skin": [
    "paras",
    "parasect",
    "jynx",
    "croagunk",
    "toxicroak",
    "helioptile",
    "heliolisk"
  ],
  "damp": [
    "paras",
    "parasect",
    "psyduck",
    "golduck",
    "poliwag",
    "poliwhirl",
    "poliwrath",
    "horsea",
    "seadra",
    "politoed",
    "wooper",
    "quagsire",
    "kingdra",
    "mudkip",
    "marshtomp",
    "swampert",
    "frillish",
    "jellicent",
    "tadbulb",
    "bellibolt"
  ],
  "wonder-skin": [
    "venomoth",
    "skitty",
    "delcatty",
    "sigilyph",
    "bruxish"
  ],
  "arena-trap": [
    "diglett",
    "dugtrio",
    "trapinch"
  ],
  "sand-force": [
    "diglett",
    "diglett-alola",
    "dugtrio",
    "dugtrio-alola",
    "steelix-mega",
    "nosepass",
    "shellos",
    "gastrodon",
    "garchomp-mega",
    "garchomp-mega-z",
    "hippopotas",
    "hippowdon",
    "probopass",
    "roggenrola",
    "boldore",
    "gigalith",
    "drilbur",
    "excadrill",
    "landorus"
  ],
  "tangling-hair": [
    "diglett-alola",
    "dugtrio-alola"
  ],
  "pickup": [
    "meowth",
    "meowth-alola",
    "meowth-galar",
    "aipom",
    "teddiursa",
    "phanpy",
    "zigzagoon",
    "zigzagoon-galar",
    "linoone",
    "linoone-galar",
    "pachirisu",
    "ambipom",
    "munchlax",
    "lillipup",
    "bunnelby",
    "diggersby",
    "dedenne",
    "pumpkaboo",
    "pumpkaboo-small",
    "pumpkaboo-large",
    "pumpkaboo-super",
    "gourgeist",
    "gourgeist-small",
    "gourgeist-large",
    "gourgeist-super",
    "pikipek",
    "trumbeak",
    "tandemaus",
    "greavard"
  ],
  "technician": [
    "meowth",
    "meowth-alola",
    "persian",
    "persian-alola",
    "mr-mime",
    "scyther",
    "scizor",
    "scizor-mega",
    "smeargle",
    "hitmontop",
    "breloom",
    "kricketune",
    "roserade",
    "ambipom",
    "mime-jr",
    "minccino",
    "cinccino",
    "marshadow",
    "toxtricity",
    "toxtricity-low-key",
    "clobbopus",
    "grapploct",
    "maushold",
    "maushold-four",
    "fezandipiti"
  ],
  "rattled": [
    "meowth-alola",
    "persian-alola",
    "magikarp",
    "ledyba",
    "sudowoodo",
    "dunsparce",
    "snubbull",
    "granbull",
    "poochyena",
    "whismur",
    "clamperl",
    "bonsly",
    "basculin-white-striped",
    "cubchoo",
    "yamper",
    "toxel",
    "wiglett",
    "wugtrio",
    "dudunsparce",
    "dudunsparce-three-segment",
    "gimmighoul"
  ],
  "limber": [
    "persian",
    "hitmonlee",
    "ditto",
    "buneary",
    "lopunny",
    "glameow",
    "purrloin",
    "liepard",
    "stunfisk",
    "hawlucha",
    "mareanie",
    "toxapex",
    "clobbopus",
    "grapploct"
  ],
  "fur-coat": [
    "persian-alola",
    "furfrou"
  ],
  "cloud-nine": [
    "psyduck",
    "golduck",
    "lickitung",
    "swablu",
    "altaria",
    "lickilicky",
    "drampa"
  ],
  "swift-swim": [
    "psyduck",
    "golduck",
    "poliwag",
    "poliwhirl",
    "poliwrath",
    "horsea",
    "goldeen",
    "seaking",
    "magikarp",
    "omanyte",
    "omastar",
    "kabuto",
    "kabutops",
    "qwilfish",
    "qwilfish-hisui",
    "mantine",
    "kingdra",
    "swampert-mega",
    "lotad",
    "lombre",
    "ludicolo",
    "surskit",
    "anorith",
    "armaldo",
    "feebas",
    "huntail",
    "gorebyss",
    "relicanth",
    "luvdisc",
    "buizel",
    "floatzel",
    "finneon",
    "lumineon",
    "mantyke",
    "tympole",
    "palpitoad",
    "seismitoad",
    "tirtouga",
    "carracosta",
    "beartic",
    "chewtle",
    "drednaw",
    "arrokuda",
    "barraskewda",
    "basculegion",
    "basculegion-f",
    "overqwil"
  ],
  "vital-spirit": [
    "mankey",
    "primeape",
    "mr-mime-galar",
    "electabuzz",
    "magmar",
    "delibird",
    "tyrogue",
    "elekid",
    "magby",
    "vigoroth",
    "electivire",
    "magmortar",
    "lillipup",
    "rockruff",
    "lycanroc-midnight",
    "annihilape"
  ],
  "anger-point": [
    "mankey",
    "primeape",
    "tauros",
    "tauros-paldea-combat",
    "tauros-paldea-blaze",
    "tauros-paldea-aqua",
    "camerupt",
    "sandile",
    "krokorok",
    "krookodile",
    "crabrawler",
    "crabominable"
  ],
  "defiant": [
    "mankey",
    "primeape",
    "farfetch-d",
    "zapdos-galar",
    "purugly",
    "pawniard",
    "bisharp",
    "braviary",
    "tornadus",
    "thundurus",
    "passimian",
    "obstagoon",
    "falinks",
    "falinks-mega",
    "annihilape",
    "kingambit",
    "ogerpon"
  ],
  "justified": [
    "growlithe",
    "arcanine",
    "absol",
    "lucario",
    "gallade",
    "cobalion",
    "terrakion",
    "virizion",
    "keldeo",
    "keldeo-resolute"
  ],
  "rock-head": [
    "growlithe-hisui",
    "arcanine-hisui",
    "geodude",
    "graveler",
    "golem",
    "onix",
    "cubone",
    "marowak",
    "marowak-alola",
    "rhyhorn",
    "rhydon",
    "aerodactyl",
    "sudowoodo",
    "steelix",
    "aron",
    "lairon",
    "aggron",
    "relicanth",
    "bagon",
    "shelgon",
    "bonsly",
    "basculin-blue-striped",
    "tyrantrum"
  ],
  "water-absorb": [
    "poliwag",
    "poliwhirl",
    "poliwrath",
    "lapras",
    "vaporeon",
    "chinchou",
    "lanturn",
    "politoed",
    "wooper",
    "wooper-paldea",
    "quagsire",
    "mantine",
    "cacnea",
    "cacturne",
    "mantyke",
    "tympole",
    "palpitoad",
    "seismitoad",
    "maractus",
    "frillish",
    "jellicent",
    "volcanion",
    "dewpider",
    "araquanid",
    "dracovish",
    "arctovish",
    "clodsire",
    "ogerpon-wellspring"
  ],
  "synchronize": [
    "abra",
    "kadabra",
    "alakazam",
    "mew",
    "natu",
    "xatu",
    "espeon",
    "umbreon",
    "ralts",
    "kirlia",
    "gardevoir",
    "munna",
    "musharna",
    "elgyem",
    "beheeyem",
    "indeedee",
    "indeedee-f",
    "rabsca"
  ],
  "trace": [
    "alakazam-mega",
    "porygon",
    "porygon2",
    "ralts",
    "kirlia",
    "gardevoir",
    "meowstic-m-mega",
    "meowstic-f-mega"
  ],
  "steadfast": [
    "machop",
    "machoke",
    "machamp",
    "farfetch-d-galar",
    "scyther",
    "mewtwo-mega-x",
    "tyrogue",
    "hitmontop",
    "riolu",
    "lucario",
    "gallade",
    "rockruff",
    "lycanroc",
    "dubwool",
    "sirfetch-d"
  ],
  "innards-out": [
    "victreebel-mega",
    "pyukumuku"
  ],
  "clear-body": [
    "tentacool",
    "tentacruel",
    "beldum",
    "metang",
    "metagross",
    "regirock",
    "regice",
    "registeel",
    "klink",
    "klang",
    "klinklang",
    "carbink",
    "diancie",
    "dreepy",
    "drakloak",
    "dragapult",
    "nacli",
    "naclstack",
    "garganacl"
  ],
  "liquid-ooze": [
    "tentacool",
    "tentacruel",
    "gulpin",
    "swalot"
  ],
  "sturdy": [
    "geodude",
    "geodude-alola",
    "graveler",
    "graveler-alola",
    "golem",
    "golem-alola",
    "magnemite",
    "magneton",
    "onix",
    "sudowoodo",
    "pineco",
    "forretress",
    "steelix",
    "shuckle",
    "skarmory",
    "donphan",
    "nosepass",
    "aron",
    "lairon",
    "aggron",
    "relicanth",
    "regirock",
    "shieldon",
    "bastiodon",
    "bonsly",
    "magnezone",
    "probopass",
    "roggenrola",
    "boldore",
    "gigalith",
    "sawk",
    "dwebble",
    "crustle",
    "tirtouga",
    "carracosta",
    "tyrunt",
    "carbink",
    "bergmite",
    "avalugg",
    "avalugg-hisui",
    "togedemaru",
    "cosmoem",
    "nacli",
    "naclstack",
    "garganacl",
    "ogerpon-cornerstone",
    "archaludon"
  ],
  "magnet-pull": [
    "geodude-alola",
    "graveler-alola",
    "golem-alola",
    "magnemite",
    "magneton",
    "nosepass",
    "magnezone",
    "probopass",
    "meltan"
  ],
  "galvanize": [
    "geodude-alola",
    "graveler-alola",
    "golem-alola"
  ],
  "flame-body": [
    "ponyta",
    "rapidash",
    "magmar",
    "moltres",
    "slugma",
    "magcargo",
    "magby",
    "magmortar",
    "heatran",
    "heatran-mega",
    "litwick",
    "lampent",
    "chandelure",
    "larvesta",
    "volcarona",
    "fletchinder",
    "talonflame",
    "carkol",
    "coalossal",
    "sizzlipede",
    "centiskorch",
    "charcadet"
  ],
  "pastel-veil": [
    "ponyta-galar",
    "rapidash-galar"
  ],
  "anticipation": [
    "ponyta-galar",
    "rapidash-galar",
    "eevee",
    "eevee-starter",
    "barboach",
    "whiscash",
    "wormadam",
    "wormadam-sandy",
    "wormadam-trash",
    "croagunk",
    "toxicroak",
    "ferrothorn",
    "hatenna",
    "hattrem",
    "hatterene",
    "flittle"
  ],
  "oblivious": [
    "slowpoke",
    "slowbro",
    "lickitung",
    "jynx",
    "slowking",
    "swinub",
    "piloswine",
    "smoochum",
    "illumise",
    "wailmer",
    "wailord",
    "numel",
    "barboach",
    "whiscash",
    "feebas",
    "spheal",
    "sealeo",
    "walrein",
    "lickilicky",
    "mamoswine",
    "salandit",
    "salazzle",
    "bounsweet",
    "steenee",
    "dondozo"
  ],
  "own-tempo": [
    "slowpoke",
    "slowpoke-galar",
    "slowbro",
    "slowbro-galar",
    "lickitung",
    "slowking",
    "slowking-galar",
    "smeargle",
    "lotad",
    "lombre",
    "ludicolo",
    "numel",
    "spoink",
    "grumpig",
    "spinda",
    "glameow",
    "purugly",
    "lickilicky",
    "petilil",
    "lilligant",
    "espurr",
    "bergmite",
    "avalugg",
    "rockruff-dusk",
    "mudbray",
    "mudsdale",
    "indeedee-f",
    "tandemaus",
    "fidough",
    "tadbulb",
    "tinkatink",
    "tinkatuff",
    "tinkaton"
  ],
  "regenerator": [
    "slowpoke",
    "slowpoke-galar",
    "slowbro",
    "slowbro-galar",
    "tangela",
    "slowking",
    "slowking-galar",
    "corsola",
    "ho-oh",
    "tangrowth",
    "audino",
    "solosis",
    "duosion",
    "reuniclus",
    "foongus",
    "amoonguss",
    "alomomola",
    "mienfoo",
    "mienshao",
    "tornadus-therian",
    "mareanie",
    "toxapex",
    "gossifleur",
    "eldegoss",
    "klawf",
    "cyclizar",
    "hydrapple"
  ],
  "shell-armor": [
    "slowbro-mega",
    "shellder",
    "cloyster",
    "krabby",
    "kingler",
    "lapras",
    "omanyte",
    "omastar",
    "torkoal",
    "corphish",
    "crawdaunt",
    "clamperl",
    "turtwig",
    "grotle",
    "torterra",
    "oshawott",
    "dewott",
    "samurott",
    "dwebble",
    "crustle",
    "escavalier",
    "shelmet",
    "sliggoo-hisui",
    "goodra-hisui",
    "turtonator",
    "chewtle",
    "drednaw",
    "klawf"
  ],
  "quick-draw": [
    "slowbro-galar"
  ],
  "analytic": [
    "magnemite",
    "magneton",
    "staryu",
    "starmie",
    "porygon",
    "porygon2",
    "magnezone",
    "porygon-z",
    "patrat",
    "watchog",
    "elgyem",
    "beheeyem"
  ],
  "scrappy": [
    "farfetch-d-galar",
    "kangaskhan",
    "miltank",
    "taillow",
    "swellow",
    "loudred",
    "exploud",
    "lopunny-mega",
    "herdier",
    "stoutland",
    "pancham",
    "pangoro",
    "decidueye-hisui",
    "sirfetch-d",
    "flamigo"
  ],
  "early-bird": [
    "doduo",
    "dodrio",
    "kangaskhan",
    "ledyba",
    "ledian",
    "natu",
    "xatu",
    "sunkern",
    "sunflora",
    "girafarig",
    "houndour",
    "houndoom",
    "seedot",
    "nuzleaf",
    "smoliv",
    "dolliv"
  ],
  "hydration": [
    "seel",
    "dewgong",
    "lapras",
    "vaporeon",
    "smoochum",
    "wingull",
    "barboach",
    "whiscash",
    "gorebyss",
    "luvdisc",
    "phione",
    "manaphy",
    "tympole",
    "palpitoad",
    "ducklett",
    "swanna",
    "alomomola",
    "shelmet",
    "accelgor",
    "goomy",
    "sliggoo",
    "goodra"
  ],
  "ice-body": [
    "seel",
    "dewgong",
    "mr-mime-galar",
    "snorunt",
    "glalie",
    "spheal",
    "sealeo",
    "walrein",
    "regice",
    "glaceon",
    "vanillite",
    "vanillish",
    "vanilluxe",
    "bergmite",
    "avalugg",
    "avalugg-hisui",
    "mr-rime",
    "arctovish",
    "frigibax",
    "arctibax",
    "baxcalibur",
    "baxcalibur-mega"
  ],
  "sticky-hold": [
    "grimer",
    "muk",
    "gulpin",
    "swalot",
    "shellos",
    "gastrodon",
    "trubbish",
    "accelgor",
    "dipplin",
    "hydrapple"
  ],
  "poison-touch": [
    "grimer",
    "grimer-alola",
    "muk",
    "muk-alola",
    "croagunk",
    "toxicroak",
    "seismitoad",
    "skrelp",
    "dragalge",
    "dragalge-mega",
    "sneasler",
    "grafaiai"
  ],
  "power-of-alchemy": [
    "grimer-alola",
    "muk-alola"
  ],
  "skill-link": [
    "shellder",
    "cloyster",
    "aipom",
    "heracross-mega",
    "ambipom",
    "minccino",
    "cinccino",
    "pikipek",
    "trumbeak",
    "toucannon"
  ],
  "overcoat": [
    "shellder",
    "cloyster",
    "pineco",
    "forretress",
    "shelgon",
    "burmy",
    "wormadam",
    "wormadam-sandy",
    "wormadam-trash",
    "sewaddle",
    "swadloon",
    "leavanny",
    "solosis",
    "duosion",
    "reuniclus",
    "escavalier",
    "shelmet",
    "vullaby",
    "mandibuzz",
    "jangmo-o",
    "hakamo-o",
    "kommo-o",
    "enamorus-therian",
    "varoom",
    "revavroom"
  ],
  "levitate": [
    "gastly",
    "haunter",
    "koffing",
    "weezing",
    "weezing-galar",
    "misdreavus",
    "unown",
    "vibrava",
    "flygon",
    "lunatone",
    "solrock",
    "baltoy",
    "claydol",
    "duskull",
    "chimecho",
    "chimecho-mega",
    "latias",
    "latias-mega",
    "latios",
    "latios-mega",
    "mismagius",
    "chingling",
    "bronzor",
    "bronzong",
    "carnivine",
    "rotom",
    "rotom-heat",
    "rotom-wash",
    "rotom-frost",
    "rotom-fan",
    "rotom-mow",
    "uxie",
    "mesprit",
    "azelf",
    "giratina-origin",
    "cresselia",
    "tynamo",
    "eelektrik",
    "eelektross",
    "eelektross-mega",
    "cryogonal",
    "hydreigon",
    "delphox-mega",
    "vikavolt"
  ],
  "cursed-body": [
    "gengar",
    "marowak-alola",
    "corsola-galar",
    "shuppet",
    "banette",
    "froslass",
    "frillish",
    "jellicent",
    "sinistea",
    "sinistea-antique",
    "polteageist",
    "polteageist-antique",
    "dreepy",
    "drakloak",
    "dragapult"
  ],
  "shadow-tag": [
    "gengar-mega",
    "wobbuffet",
    "wynaut",
    "gothita",
    "gothorita",
    "gothitelle"
  ],
  "weak-armor": [
    "onix",
    "omanyte",
    "omastar",
    "kabuto",
    "kabutops",
    "slugma",
    "magcargo",
    "corsola-galar",
    "skarmory",
    "roggenrola",
    "boldore",
    "dwebble",
    "crustle",
    "garbodor",
    "vanillite",
    "vanillish",
    "vanilluxe",
    "vullaby",
    "mandibuzz",
    "sinistea",
    "sinistea-antique",
    "polteageist",
    "polteageist-antique",
    "cursola",
    "armarouge",
    "ceruledge"
  ],
  "insomnia": [
    "drowzee",
    "hypno",
    "mewtwo-mega-y",
    "hoothoot",
    "noctowl",
    "spinarak",
    "ariados",
    "murkrow",
    "delibird",
    "shuppet",
    "banette",
    "honchkrow",
    "pumpkaboo",
    "pumpkaboo-small",
    "pumpkaboo-large",
    "pumpkaboo-super",
    "gourgeist",
    "gourgeist-small",
    "gourgeist-large",
    "gourgeist-super",
    "tarountula",
    "spidops",
    "capsakid",
    "scovillain"
  ],
  "forewarn": [
    "drowzee",
    "hypno",
    "jynx",
    "smoochum",
    "munna",
    "musharna"
  ],
  "hyper-cutter": [
    "krabby",
    "kingler",
    "pinsir",
    "gligar",
    "mawile",
    "trapinch",
    "corphish",
    "crawdaunt",
    "gliscor",
    "crabrawler",
    "crabominable"
  ],
  "soundproof": [
    "voltorb",
    "voltorb-hisui",
    "electrode",
    "electrode-hisui",
    "mr-mime",
    "whismur",
    "loudred",
    "exploud",
    "shieldon",
    "bastiodon",
    "mime-jr",
    "snover",
    "abomasnow",
    "bouffalant",
    "jangmo-o",
    "hakamo-o",
    "kommo-o"
  ],
  "aftermath": [
    "voltorb",
    "voltorb-hisui",
    "electrode",
    "electrode-hisui",
    "drifloon",
    "drifblim",
    "stunky",
    "skuntank",
    "trubbish",
    "garbodor"
  ],
  "harvest": [
    "exeggcute",
    "exeggutor",
    "exeggutor-alola",
    "tropius",
    "phantump",
    "trevenant",
    "smoliv",
    "dolliv",
    "arboliva"
  ],
  "battle-armor": [
    "cubone",
    "marowak",
    "kabuto",
    "kabutops",
    "anorith",
    "armaldo",
    "skorupi",
    "drapion",
    "type-null",
    "perrserker",
    "falinks",
    "falinks-mega"
  ],
  "reckless": [
    "hitmonlee",
    "rhyhorn",
    "rhydon",
    "starly",
    "staravia",
    "staraptor",
    "staraptor-mega",
    "rhyperior",
    "emboar",
    "basculin",
    "mienfoo",
    "mienshao",
    "bouffalant",
    "obstagoon"
  ],
  "unburden": [
    "hitmonlee",
    "treecko",
    "grovyle",
    "sceptile",
    "drifloon",
    "drifblim",
    "purrloin",
    "liepard",
    "accelgor",
    "swirlix",
    "slurpuff",
    "hawlucha",
    "nickit",
    "thievul",
    "sneasler",
    "shroodle",
    "grafaiai"
  ],
  "iron-fist": [
    "hitmonchan",
    "ledian",
    "chimchar",
    "monferno",
    "infernape",
    "timburr",
    "gurdurr",
    "conkeldurr",
    "golett",
    "golurk",
    "pancham",
    "pangoro",
    "crabrawler",
    "crabominable",
    "crabominable-mega",
    "melmetal",
    "pawmi",
    "pawmo",
    "pawmot"
  ],
  "neutralizing-gas": [
    "koffing",
    "weezing",
    "weezing-galar"
  ],
  "misty-surge": [
    "weezing-galar",
    "tapu-fini"
  ],
  "natural-cure": [
    "chansey",
    "staryu",
    "starmie",
    "corsola",
    "blissey",
    "celebi",
    "roselia",
    "swablu",
    "altaria",
    "budew",
    "roserade",
    "happiny",
    "shaymin",
    "phantump",
    "trevenant",
    "comfey",
    "pawmi",
    "pawmo",
    "pawmot"
  ],
  "serene-grace": [
    "chansey",
    "togepi",
    "togetic",
    "dunsparce",
    "blissey",
    "jirachi",
    "happiny",
    "togekiss",
    "shaymin-sky",
    "deerling",
    "sawsbuck",
    "meloetta",
    "meloetta-pirouette",
    "dudunsparce",
    "dudunsparce-three-segment"
  ],
  "healer": [
    "chansey",
    "bellossom",
    "blissey",
    "audino",
    "audino-mega",
    "alomomola",
    "spritzee",
    "aromatisse",
    "hatenna",
    "hattrem",
    "hatterene"
  ],
  "leaf-guard": [
    "tangela",
    "chikorita",
    "bayleef",
    "meganium",
    "hoppip",
    "skiploom",
    "jumpluff",
    "roselia",
    "budew",
    "tangrowth",
    "leafeon",
    "swadloon",
    "petilil",
    "lilligant",
    "lilligant-hisui",
    "fomantis",
    "lurantis",
    "bounsweet",
    "steenee",
    "tsareena",
    "zarude",
    "zarude-dada"
  ],
  "parental-bond": [
    "kangaskhan-mega"
  ],
  "water-veil": [
    "goldeen",
    "seaking",
    "mantine",
    "wailmer",
    "wailord",
    "huntail",
    "buizel",
    "floatzel",
    "finneon",
    "lumineon",
    "mantyke",
    "finizen",
    "dondozo"
  ],
  "illuminate": [
    "staryu",
    "starmie",
    "chinchou",
    "lanturn",
    "volbeat",
    "watchog",
    "morelull",
    "shiinotic"
  ],
  "huge-power": [
    "starmie-mega",
    "marill",
    "azumarill",
    "azurill",
    "mawile-mega",
    "bunnelby",
    "diggersby"
  ],
  "filter": [
    "mr-mime",
    "aggron-mega",
    "mime-jr",
    "revavroom"
  ],
  "screen-cleaner": [
    "mr-mime-galar",
    "mr-rime"
  ],
  "mold-breaker": [
    "pinsir",
    "gyarados-mega",
    "ampharos-mega",
    "cranidos",
    "rampardos",
    "emboar-mega",
    "drilbur",
    "excadrill",
    "throh",
    "sawk",
    "basculin",
    "basculin-blue-striped",
    "basculin-white-striped",
    "axew",
    "fraxure",
    "haxorus",
    "druddigon",
    "pancham",
    "pangoro",
    "hawlucha",
    "basculegion",
    "basculegion-f",
    "tinkatink",
    "tinkatuff",
    "tinkaton",
    "veluza",
    "ogerpon-hearthflame"
  ],
  "moxie": [
    "pinsir",
    "gyarados",
    "heracross",
    "mightyena",
    "salamence",
    "honchkrow",
    "sandile",
    "krokorok",
    "krookodile",
    "scraggy",
    "scrafty",
    "scrafty-mega",
    "litleo",
    "pyroar",
    "pyroar-mega",
    "quaxly",
    "quaxwell",
    "quaquaval"
  ],
  "aerilate": [
    "pinsir-mega",
    "salamence-mega"
  ],
  "cud-chew": [
    "tauros-paldea-combat",
    "tauros-paldea-blaze",
    "tauros-paldea-aqua",
    "farigiraf"
  ],
  "imposter": [
    "ditto"
  ],
  "volt-absorb": [
    "jolteon",
    "chinchou",
    "lanturn",
    "minun",
    "pachirisu",
    "thundurus-therian",
    "zeraora",
    "zeraora-mega",
    "dracozolt",
    "arctozolt",
    "pawmo",
    "pawmot",
    "wattrel",
    "kilowattrel"
  ],
  "quick-feet": [
    "jolteon",
    "granbull",
    "teddiursa",
    "ursaring",
    "poochyena",
    "mightyena",
    "zigzagoon",
    "zigzagoon-galar",
    "linoone",
    "linoone-galar",
    "shroomish"
  ],
  "download": [
    "porygon",
    "porygon2",
    "porygon-z",
    "genesect",
    "genesect-douse",
    "genesect-shock",
    "genesect-burn",
    "genesect-chill"
  ],
  "pressure": [
    "aerodactyl",
    "articuno",
    "zapdos",
    "moltres",
    "mewtwo",
    "raikou",
    "entei",
    "suicune",
    "lugia",
    "ho-oh",
    "wailmer",
    "wailord",
    "dusclops",
    "absol",
    "deoxys",
    "deoxys-attack",
    "deoxys-defense",
    "deoxys-speed",
    "vespiquen",
    "spiritomb",
    "weavile",
    "dusknoir",
    "dialga",
    "dialga-origin",
    "palkia",
    "palkia-origin",
    "giratina",
    "pawniard",
    "bisharp",
    "kyurem",
    "corviknight",
    "eternatus",
    "sneasler",
    "kingambit"
  ],
  "immunity": [
    "snorlax",
    "gligar",
    "zangoose"
  ],
  "berserk": [
    "moltres-galar",
    "drampa",
    "drampa-mega"
  ],
  "marvel-scale": [
    "dratini",
    "dragonair",
    "milotic"
  ],
  "multiscale": [
    "dragonite",
    "dragonite-mega",
    "lugia"
  ],
  "mega-sol": [
    "meganium-mega"
  ],
  "dragonize": [
    "feraligatr-mega"
  ],
  "super-luck": [
    "togepi",
    "togetic",
    "murkrow",
    "absol",
    "honchkrow",
    "togekiss",
    "pidove",
    "tranquill",
    "unfezant"
  ],
  "plus": [
    "mareep",
    "flaaffy",
    "ampharos",
    "plusle",
    "klink",
    "klang",
    "klinklang",
    "dedenne",
    "toxtricity"
  ],
  "sap-sipper": [
    "marill",
    "azumarill",
    "girafarig",
    "stantler",
    "miltank",
    "azurill",
    "blitzle",
    "zebstrika",
    "deerling",
    "sawsbuck",
    "bouffalant",
    "skiddo",
    "gogoat",
    "goomy",
    "sliggoo",
    "sliggoo-hisui",
    "goodra",
    "goodra-hisui",
    "drampa",
    "wyrdeer",
    "farigiraf"
  ],
  "drizzle": [
    "politoed",
    "pelipper",
    "kyogre"
  ],
  "speed-boost": [
    "yanma",
    "torchic",
    "combusken",
    "blaziken",
    "blaziken-mega",
    "ninjask",
    "carvanha",
    "sharpedo",
    "yanmega",
    "venipede",
    "whirlipede",
    "scolipede",
    "scolipede-mega",
    "flittle",
    "espathra"
  ],
  "prankster": [
    "murkrow",
    "sableye",
    "volbeat",
    "illumise",
    "banette-mega",
    "riolu",
    "purrloin",
    "liepard",
    "cottonee",
    "whimsicott",
    "tornadus",
    "thundurus",
    "meowstic",
    "klefki",
    "impidimp",
    "morgrem",
    "grimmsnarl",
    "shroodle",
    "grafaiai"
  ],
  "curious-medicine": [
    "slowking-galar"
  ],
  "telepathy": [
    "wobbuffet",
    "ralts",
    "kirlia",
    "gardevoir",
    "meditite",
    "medicham",
    "wynaut",
    "dialga",
    "dialga-origin",
    "palkia",
    "palkia-origin",
    "giratina",
    "munna",
    "musharna",
    "elgyem",
    "beheeyem",
    "noibat",
    "noivern",
    "oranguru",
    "tapu-koko",
    "tapu-lele",
    "tapu-bulu",
    "tapu-fini",
    "blipbug",
    "dottler",
    "orbeetle",
    "rabsca"
  ],
  "light-metal": [
    "scizor",
    "beldum",
    "metang",
    "metagross",
    "registeel",
    "duraludon"
  ],
  "contrary": [
    "shuckle",
    "spinda",
    "snivy",
    "servine",
    "serperior",
    "inkay",
    "malamar",
    "malamar-mega",
    "fomantis",
    "lurantis",
    "enamorus"
  ],
  "pickpocket": [
    "sneasel",
    "sneasel-hisui",
    "seedot",
    "nuzleaf",
    "shiftry",
    "weavile",
    "binacle",
    "barbaracle",
    "barbaracle-mega",
    "impidimp",
    "morgrem",
    "grimmsnarl",
    "shroodle",
    "tinkatink",
    "tinkatuff",
    "tinkaton"
  ],
  "honey-gather": [
    "teddiursa",
    "combee",
    "cutiefly",
    "ribombee"
  ],
  "magma-armor": [
    "slugma",
    "magcargo",
    "camerupt"
  ],
  "moody": [
    "remoraid",
    "octillery",
    "smeargle",
    "snorunt",
    "glalie",
    "bidoof",
    "bibarel",
    "scovillain"
  ],
  "suction-cups": [
    "octillery",
    "lileep",
    "cradily",
    "inkay",
    "malamar",
    "malamar-mega"
  ],
  "stalwart": [
    "skarmory-mega",
    "duraludon",
    "archaludon"
  ],
  "sand-stream": [
    "tyranitar",
    "tyranitar-mega",
    "hippopotas",
    "hippowdon",
    "gigalith"
  ],
  "wind-rider": [
    "shiftry",
    "bramblin",
    "brambleghast"
  ],
  "pixilate": [
    "gardevoir-mega",
    "altaria-mega",
    "sylveon"
  ],
  "poison-heal": [
    "shroomish",
    "breloom",
    "gliscor"
  ],
  "truant": [
    "slakoth",
    "slaking",
    "durant"
  ],
  "wonder-guard": [
    "shedinja"
  ],
  "normalize": [
    "skitty",
    "delcatty"
  ],
  "stall": [
    "sableye"
  ],
  "heavy-metal": [
    "aron",
    "lairon",
    "aggron",
    "bronzor",
    "bronzong",
    "cufant",
    "copperajah",
    "duraludon"
  ],
  "pure-power": [
    "meditite",
    "medicham",
    "medicham-mega"
  ],
  "minus": [
    "electrike",
    "manectric",
    "minun",
    "klink",
    "klang",
    "klinklang",
    "toxtricity-low-key"
  ],
  "rough-skin": [
    "carvanha",
    "sharpedo",
    "gible",
    "gabite",
    "garchomp",
    "druddigon"
  ],
  "strong-jaw": [
    "sharpedo-mega",
    "tyrunt",
    "tyrantrum",
    "avalugg-hisui",
    "yungoos",
    "gumshoos",
    "bruxish",
    "chewtle",
    "drednaw",
    "boltund",
    "dracovish"
  ],
  "simple": [
    "numel",
    "bidoof",
    "bibarel",
    "woobat",
    "swoobat"
  ],
  "solid-rock": [
    "camerupt",
    "rhyperior",
    "tirtouga",
    "carracosta"
  ],
  "white-smoke": [
    "torkoal",
    "heatmor",
    "sizzlipede",
    "centiskorch"
  ],
  "toxic-boost": [
    "zangoose"
  ],
  "storm-drain": [
    "lileep",
    "cradily",
    "shellos",
    "gastrodon",
    "finneon",
    "lumineon",
    "maractus",
    "tatsugiri",
    "tatsugiri-droopy",
    "tatsugiri-stretchy",
    "tatsugiri-curly-mega",
    "tatsugiri-droopy-mega",
    "tatsugiri-stretchy-mega"
  ],
  "forecast": [
    "castform",
    "castform-sunny",
    "castform-rainy",
    "castform-snowy"
  ],
  "color-change": [
    "kecleon"
  ],
  "protean": [
    "kecleon",
    "froakie",
    "frogadier",
    "greninja",
    "greninja-mega",
    "sprigatito",
    "floragato",
    "meowscarada"
  ],
  "refrigerate": [
    "glalie-mega",
    "amaura",
    "aurorus"
  ],
  "primordial-sea": [
    "kyogre-primal"
  ],
  "desolate-land": [
    "groudon-primal"
  ],
  "air-lock": [
    "rayquaza"
  ],
  "delta-stream": [
    "rayquaza-mega"
  ],
  "flower-gift": [
    "cherrim",
    "cherrim-sunshine"
  ],
  "flare-boost": [
    "drifloon",
    "drifblim"
  ],
  "klutz": [
    "buneary",
    "lopunny",
    "woobat",
    "swoobat",
    "audino",
    "golett",
    "golurk",
    "stufful",
    "bewear",
    "toxel",
    "fidough",
    "capsakid"
  ],
  "heatproof": [
    "bronzor",
    "bronzong",
    "rolycoly",
    "poltchageist",
    "poltchageist-artisan",
    "sinistcha",
    "sinistcha-masterpiece"
  ],
  "motor-drive": [
    "electivire",
    "blitzle",
    "zebstrika",
    "emolga"
  ],
  "sharpness": [
    "gallade",
    "samurott-hisui",
    "kleavor",
    "veluza"
  ],
  "slow-start": [
    "regigigas",
    "varoom"
  ],
  "bad-dreams": [
    "darkrai",
    "darkrai-mega"
  ],
  "multitype": [
    "arceus",
    "arceus-bug",
    "arceus-dark",
    "arceus-dragon",
    "arceus-electric",
    "arceus-fairy",
    "arceus-fighting",
    "arceus-fire",
    "arceus-flying",
    "arceus-ghost",
    "arceus-grass",
    "arceus-ground",
    "arceus-ice",
    "arceus-poison",
    "arceus-psychic",
    "arceus-rock",
    "arceus-steel",
    "arceus-water"
  ],
  "victory-star": [
    "victini"
  ],
  "piercing-drill": [
    "excadrill-mega"
  ],
  "zen-mode": [
    "darmanitan",
    "darmanitan-zen",
    "darmanitan-galar",
    "darmanitan-galar-zen"
  ],
  "gorilla-tactics": [
    "darmanitan-galar"
  ],
  "mummy": [
    "yamask",
    "cofagrigus"
  ],
  "wandering-spirit": [
    "yamask-galar",
    "runerigus"
  ],
  "defeatist": [
    "archen",
    "archeops"
  ],
  "illusion": [
    "zorua",
    "zorua-hisui",
    "zoroark",
    "zoroark-hisui"
  ],
  "iron-barbs": [
    "ferroseed",
    "ferrothorn",
    "togedemaru"
  ],
  "mimicry": [
    "stunfisk-galar"
  ],
  "unseen-fist": [
    "golurk-mega",
    "urshifu",
    "urshifu-rapid-strike"
  ],
  "turboblaze": [
    "reshiram",
    "kyurem-white"
  ],
  "teravolt": [
    "zekrom",
    "kyurem-black"
  ],
  "bulletproof": [
    "chespin",
    "quilladin",
    "chesnaught",
    "chesnaught-mega",
    "jangmo-o",
    "hakamo-o",
    "kommo-o",
    "wooloo",
    "dubwool",
    "applin",
    "ursaluna"
  ],
  "magician": [
    "fennekin",
    "braixen",
    "delphox",
    "klefki",
    "hoopa",
    "hoopa-unbound"
  ],
  "battle-bond": [
    "greninja-bond",
    "greninja-ash"
  ],
  "cheek-pouch": [
    "bunnelby",
    "diggersby",
    "dedenne",
    "skwovet",
    "greedent",
    "maushold",
    "maushold-four"
  ],
  "gale-wings": [
    "fletchling",
    "fletchinder",
    "talonflame"
  ],
  "flower-veil": [
    "flabe-be",
    "floette",
    "floette-eternal",
    "florges",
    "comfey"
  ],
  "symbiosis": [
    "flabe-be",
    "floette",
    "floette-eternal",
    "florges",
    "oranguru"
  ],
  "fairy-aura": [
    "floette-mega",
    "xerneas",
    "xerneas-neutral"
  ],
  "grass-pelt": [
    "skiddo",
    "gogoat"
  ],
  "stance-change": [
    "aegislash",
    "aegislash-blade"
  ],
  "aroma-veil": [
    "spritzee",
    "aromatisse",
    "milcery",
    "alcremie",
    "lechonk",
    "oinkologne-f",
    "dachsbun"
  ],
  "sweet-veil": [
    "swirlix",
    "slurpuff",
    "cutiefly",
    "ribombee",
    "bounsweet",
    "steenee",
    "tsareena",
    "milcery",
    "alcremie"
  ],
  "gooey": [
    "goomy",
    "sliggoo",
    "sliggoo-hisui",
    "goodra",
    "goodra-hisui",
    "wiglett",
    "wugtrio"
  ],
  "dark-aura": [
    "yveltal"
  ],
  "aura-break": [
    "zygarde",
    "zygarde-10",
    "zygarde-mega"
  ],
  "power-construct": [
    "zygarde-complete"
  ],
  "long-reach": [
    "rowlet",
    "dartrix",
    "decidueye"
  ],
  "liquid-voice": [
    "popplio",
    "brionne",
    "primarina"
  ],
  "stakeout": [
    "yungoos",
    "gumshoos",
    "nickit",
    "thievul",
    "tarountula",
    "spidops",
    "maschiff",
    "mabosstiff"
  ],
  "battery": [
    "charjabug"
  ],
  "dancer": [
    "oricorio",
    "oricorio-pom-pom",
    "oricorio-pau",
    "oricorio-sensu"
  ],
  "schooling": [
    "wishiwashi",
    "wishiwashi-school"
  ],
  "merciless": [
    "mareanie",
    "toxapex"
  ],
  "stamina": [
    "mudbray",
    "mudsdale",
    "archaludon"
  ],
  "water-bubble": [
    "dewpider",
    "araquanid"
  ],
  "corrosion": [
    "salandit",
    "salazzle",
    "glimmet",
    "glimmora"
  ],
  "fluffy": [
    "stufful",
    "bewear",
    "wooloo",
    "dubwool",
    "greavard",
    "houndstone"
  ],
  "queenly-majesty": [
    "tsareena"
  ],
  "triage": [
    "comfey"
  ],
  "receiver": [
    "passimian"
  ],
  "wimp-out": [
    "wimpod"
  ],
  "emergency-exit": [
    "golisopod",
    "golisopod-mega"
  ],
  "water-compaction": [
    "sandygast",
    "palossand"
  ],
  "rks-system": [
    "silvally",
    "silvally-bug",
    "silvally-dark",
    "silvally-dragon",
    "silvally-electric",
    "silvally-fairy",
    "silvally-fighting",
    "silvally-fire",
    "silvally-flying",
    "silvally-ghost",
    "silvally-grass",
    "silvally-ground",
    "silvally-ice",
    "silvally-poison",
    "silvally-psychic",
    "silvally-rock",
    "silvally-steel",
    "silvally-water"
  ],
  "shields-down": [
    "minior",
    "minior-meteor"
  ],
  "comatose": [
    "komala"
  ],
  "disguise": [
    "mimikyu",
    "mimikyu-busted"
  ],
  "dazzling": [
    "bruxish"
  ],
  "steelworker": [
    "dhelmise"
  ],
  "electric-surge": [
    "tapu-koko",
    "pincurchin"
  ],
  "psychic-surge": [
    "tapu-lele",
    "indeedee",
    "indeedee-f"
  ],
  "grassy-surge": [
    "tapu-bulu",
    "grookey",
    "thwackey",
    "rillaboom"
  ],
  "full-metal-body": [
    "solgaleo"
  ],
  "shadow-shield": [
    "lunala"
  ],
  "beast-boost": [
    "nihilego",
    "buzzwole",
    "pheromosa",
    "xurkitree",
    "celesteela",
    "kartana",
    "guzzlord",
    "poipole",
    "naganadel",
    "stakataka",
    "blacephalon"
  ],
  "prism-armor": [
    "necrozma",
    "necrozma-dusk-mane",
    "necrozma-dawn-wings"
  ],
  "neuroforce": [
    "necrozma-ultra"
  ],
  "soul-heart": [
    "magearna",
    "magearna-original",
    "magearna-mega",
    "magearna-original-mega"
  ],
  "libero": [
    "scorbunny",
    "raboot",
    "cinderace"
  ],
  "mirror-armor": [
    "corviknight"
  ],
  "cotton-down": [
    "gossifleur",
    "eldegoss"
  ],
  "ball-fetch": [
    "yamper"
  ],
  "steam-engine": [
    "rolycoly",
    "carkol",
    "coalossal"
  ],
  "ripen": [
    "applin",
    "flapple",
    "appletun"
  ],
  "sand-spit": [
    "silicobra",
    "sandaconda"
  ],
  "gulp-missile": [
    "cramorant",
    "cramorant-gulping",
    "cramorant-gorging"
  ],
  "propeller-tail": [
    "arrokuda",
    "barraskewda"
  ],
  "punk-rock": [
    "toxtricity",
    "toxtricity-low-key"
  ],
  "steely-spirit": [
    "perrserker"
  ],
  "perish-body": [
    "cursola"
  ],
  "ice-scales": [
    "snom",
    "frosmoth"
  ],
  "power-spot": [
    "stonjourner"
  ],
  "ice-face": [
    "eiscue",
    "eiscue-noice"
  ],
  "hunger-switch": [
    "morpeko",
    "morpeko-hangry"
  ],
  "intrepid-sword": [
    "zacian",
    "zacian-crowned"
  ],
  "dauntless-shield": [
    "zamazenta",
    "zamazenta-crowned"
  ],
  "transistor": [
    "regieleki"
  ],
  "dragons-maw": [
    "regidrago"
  ],
  "chilling-neigh": [
    "glastrier"
  ],
  "grim-neigh": [
    "spectrier"
  ],
  "as-one-glastrier": [
    "calyrex-ice"
  ],
  "as-one-spectrier": [
    "calyrex-shadow"
  ],
  "minds-eye": [
    "ursaluna-bloodmoon"
  ],
  "lingering-aroma": [
    "oinkologne"
  ],
  "well-baked-body": [
    "dachsbun"
  ],
  "seed-sower": [
    "arboliva"
  ],
  "purifying-salt": [
    "nacli",
    "naclstack",
    "garganacl"
  ],
  "electromorphosis": [
    "bellibolt"
  ],
  "wind-power": [
    "wattrel",
    "kilowattrel"
  ],
  "guard-dog": [
    "mabosstiff",
    "okidogi"
  ],
  "mycelium-might": [
    "toedscool",
    "toedscruel"
  ],
  "anger-shell": [
    "klawf"
  ],
  "spicy-spray": [
    "scovillain-mega"
  ],
  "opportunist": [
    "espathra"
  ],
  "rocky-payload": [
    "bombirdier"
  ],
  "zero-to-hero": [
    "palafin",
    "palafin-hero"
  ],
  "earth-eater": [
    "orthworm"
  ],
  "toxic-debris": [
    "glimmet",
    "glimmora"
  ],
  "costar": [
    "flamigo"
  ],
  "commander": [
    "tatsugiri",
    "tatsugiri-droopy",
    "tatsugiri-stretchy",
    "tatsugiri-curly-mega",
    "tatsugiri-droopy-mega",
    "tatsugiri-stretchy-mega"
  ],
  "armor-tail": [
    "farigiraf"
  ],
  "supreme-overlord": [
    "kingambit"
  ],
  "protosynthesis": [
    "great-tusk",
    "scream-tail",
    "brute-bonnet",
    "flutter-mane",
    "slither-wing",
    "sandy-shocks",
    "roaring-moon",
    "walking-wake",
    "gouging-fire",
    "raging-bolt"
  ],
  "quark-drive": [
    "iron-treads",
    "iron-bundle",
    "iron-hands",
    "iron-jugulis",
    "iron-moth",
    "iron-thorns",
    "iron-valiant",
    "iron-leaves",
    "iron-boulder",
    "iron-crown"
  ],
  "thermal-exchange": [
    "frigibax",
    "arctibax",
    "baxcalibur",
    "baxcalibur-mega"
  ],
  "good-as-gold": [
    "gholdengo"
  ],
  "tablets-of-ruin": [
    "wo-chien"
  ],
  "sword-of-ruin": [
    "chien-pao"
  ],
  "vessel-of-ruin": [
    "ting-lu"
  ],
  "beads-of-ruin": [
    "chi-yu"
  ],
  "orichalcum-pulse": [
    "koraidon"
  ],
  "hadron-engine": [
    "miraidon"
  ],
  "supersweet-syrup": [
    "dipplin",
    "hydrapple"
  ],
  "hospitality": [
    "poltchageist",
    "poltchageist-artisan",
    "sinistcha",
    "sinistcha-masterpiece"
  ],
  "toxic-chain": [
    "okidogi",
    "munkidori",
    "fezandipiti"
  ],
  "embody-aspect-teal": [
    "ogerpon-teal-tera"
  ],
  "embody-aspect-wellspring": [
    "ogerpon-wellspring-tera"
  ],
  "embody-aspect-hearthflame": [
    "ogerpon-hearthflame-tera"
  ],
  "embody-aspect-cornerstone": [
    "ogerpon-cornerstone-tera"
  ],
  "tera-shift": [
    "terapagos"
  ],
  "tera-shell": [
    "terapagos-terastal"
  ],
  "teraform-zero": [
    "terapagos-stellar"
  ],
  "poison-puppeteer": [
    "pecharunt"
  ]
}